pythonProjectManager/__init__.py
pythonProjectManager/content.py
pythonProjectManager/main.py
sparrowPythonProjectManager-0.1.dist-info/METADATA
sparrowPythonProjectManager-0.1.dist-info/WHEEL
sparrowPythonProjectManager-0.1.dist-info/top_level.txt
sparrowPythonProjectManager-0.1.dist-info/RECORD
