Metadata-Version: 2.1
Name: sparrowPythonProjectManager
Version: 0.1
Summary: Python包管理工具
